.gitignore
.travis.yml
CHANGES.rst
Makefile
README.rst
TODO.rst
requirements.txt
runtests.py
setup.py
docs/Makefile
docs/api.rst
docs/changelog.rst
docs/conf.py
docs/development.rst
docs/glossary.rst
docs/index.rst
docs/make.bat
docs/_themes/queuey-py/layout.html
docs/_themes/queuey-py/theme.conf
etc/queuey.ini
etc/supervisord.conf
etc/nginx/fastcgi.conf
etc/nginx/fastcgi.conf.default
etc/nginx/fastcgi_params
etc/nginx/fastcgi_params.default
etc/nginx/koi-utf
etc/nginx/koi-win
etc/nginx/mime.types
etc/nginx/mime.types.default
etc/nginx/nginx.conf
etc/nginx/nginx.conf.default
etc/nginx/scgi_params
etc/nginx/scgi_params.default
etc/nginx/uwsgi_params
etc/nginx/uwsgi_params.default
etc/nginx/win-utf
etc/ssl/README.txt
etc/ssl/invalid.crt
etc/ssl/invalid.csr
etc/ssl/invalid.key
etc/ssl/localhost.crt
etc/ssl/localhost.csr
etc/ssl/localhost.key
etc/ssl/privkey.pem
queuey_py/__init__.py
queuey_py/client.py
queuey_py/tests.py
queuey_py.egg-info/PKG-INFO
queuey_py.egg-info/SOURCES.txt
queuey_py.egg-info/dependency_links.txt
queuey_py.egg-info/not-zip-safe
queuey_py.egg-info/requires.txt
queuey_py.egg-info/top_level.txt
sw/virtualenv.py